poocr/__init__.py
poocr/api/__init__.py
poocr/api/ocr.py
poocr/api/ocr2excel.py
poocr/core/BaiduOCR.py
poocr/core/HuaweiOCR.py
poocr/core/OCR.py
poocr/core/__init__.py
poocr/lib/CommonUtils.py
poocr/lib/Config.py
poocr/lib/Const.py
poocr/lib/__init__.py
poocr/lib/apig_sdk/__init__.py
poocr/lib/apig_sdk/signer.py
tests/__init__.py
tests/test_tencent.py
json4excel-0.0.1.dist-info/LICENSE
json4excel-0.0.1.dist-info/METADATA
json4excel-0.0.1.dist-info/WHEEL
json4excel-0.0.1.dist-info/top_level.txt
json4excel-0.0.1.dist-info/RECORD
