Metadata-Version: 2.1
Name: json4excel
Version: 0.0.1
Summary: pip install json4excel
Home-page: https://www.python-office.com/
Author: CoderWanFeng
Author-email: 1957875073@qq.com
License: MIT
Project-URL: Bug Tracker, https://github.com/CoderWanFeng/json4excel/issues
Project-URL: Documentation, https://github.com/CoderWanFeng/json4excel/blob/main/README.md
Project-URL: Source Code, https://github.com/CoderWanFeng/json4excel
Platform: any
Requires-Python: >=3.7
License-File: LICENSE
Requires-Dist: toml
Requires-Dist: tencentcloud-sdk-python
Requires-Dist: poprogress
Requires-Dist: pofile
Requires-Dist: pandas
Requires-Dist: pocode
Requires-Dist: huaweicloudsdkocr
Requires-Dist: huaweicloudsdkcore
Requires-Dist: loguru
